.travis.yml
MANIFEST.in
README.rst
setup.py
djongo_optimistic_lock.egg-info/PKG-INFO
djongo_optimistic_lock.egg-info/SOURCES.txt
djongo_optimistic_lock.egg-info/dependency_links.txt
djongo_optimistic_lock.egg-info/requires.txt
djongo_optimistic_lock.egg-info/top_level.txt
dol/__init__.py
tests/manage.py
tests/tests/__init__.py
tests/tests/admin.py
tests/tests/forms.py
tests/tests/models.py
tests/tests/settings.py
tests/tests/sqlite_settings.py
tests/tests/tests.py
tests/tests/travis_settings.py
tests/tests/urls.py
tests/tests/views.py