Metadata-Version: 1.1
Name: djongo-optimistic-lock
Version: 1.0.1.dev0
Summary: Offline optimistic locking for Django (with Djongo)
Home-page: https://github.com/noelpuru/djongo-optimistic-lock
Author: Gavin Wahl
Author-email: gavinwahl@gmail.com
License: BSD
Platform: UNKNOWN
Classifier: Development Status :: 4 - Beta
Classifier: Environment :: Web Environment
Classifier: Framework :: Django
Classifier: Intended Audience :: Developers
Classifier: License :: OSI Approved :: BSD License
Classifier: Programming Language :: Python
Classifier: Programming Language :: Python :: 2.7
Classifier: Programming Language :: Python :: 3.4
Classifier: Programming Language :: Python :: 3.5
Classifier: Programming Language :: Python :: 3.6
